Aldebaran/__init__.py
Aldebaran/algo_response.py
Aldebaran/algorithm.py
Aldebaran/async_response.py
Aldebaran/client.py
Aldebaran/data.py
Aldebaran/datadirectory.py
Aldebaran/datafile.py
Aldebaran/errors.py
Aldebaran/util.py
aldebaran-0.1.2.dist-info/METADATA
aldebaran-0.1.2.dist-info/WHEEL
aldebaran-0.1.2.dist-info/top_level.txt
aldebaran-0.1.2.dist-info/RECORD
